aiogram_sentry/__init__.py
aiogram_sentry-0.1.0.dist-info/LICENSE
aiogram_sentry-0.1.0.dist-info/METADATA
aiogram_sentry-0.1.0.dist-info/WHEEL
aiogram_sentry-0.1.0.dist-info/RECORD
